EvaMap/EvaMap.py
EvaMap/__init__.py
EvaMap/Dimensions/Availability.py
EvaMap/Dimensions/Clarity.py
EvaMap/Dimensions/Conciseness.py
EvaMap/Dimensions/Connectability.py
EvaMap/Dimensions/Consistency.py
EvaMap/Dimensions/Coverability.py
EvaMap/Dimensions/Dimension.py
EvaMap/Dimensions/__init__.py
EvaMap/Metrics/A_Error.py
EvaMap/Metrics/__init__.py
EvaMap/Metrics/disjointWith.py
EvaMap/Metrics/domainRange.py
EvaMap/Metrics/duplicatedRules.py
EvaMap/Metrics/equivalentClassesProperties.py
EvaMap/Metrics/existingVocab.py
EvaMap/Metrics/externalLink.py
EvaMap/Metrics/externalURIs.py
EvaMap/Metrics/humanDesc.py
EvaMap/Metrics/humanReadable.py
EvaMap/Metrics/localLink.py
EvaMap/Metrics/localLinks.py
EvaMap/Metrics/longTerm.py
EvaMap/Metrics/longURI.py
EvaMap/Metrics/metric.py
EvaMap/Metrics/sameAs.py
EvaMap/Metrics/subClassesProperties.py
EvaMap/Metrics/verticalCoverage.py
EvaMap/examples/__init__.py
EvaMap/examples/data.py
EvaMap/examples/mapping.py
EvaMap/examples/ontology.py
EvaMap/utils/__init__.py
EvaMap/utils/yarrrml_parser.py
EvaMap-2.0.6.dist-info/LICENSE
EvaMap-2.0.6.dist-info/METADATA
EvaMap-2.0.6.dist-info/WHEEL
EvaMap-2.0.6.dist-info/top_level.txt
EvaMap-2.0.6.dist-info/RECORD
