Metadata-Version: 2.1
Name: EvaMap
Version: 2.0.6
Summary: A python library that can assess the quality of an RDF mapping
Home-page: https://github.com/benjimor/EvaMap
Author: benjimor
Author-email: benjimor44@gmail.com
License: MIT
Keywords: rdf,mapping,semantic web,research
Platform: UNKNOWN
Classifier: Programming Language :: Python :: 3
Classifier: License :: OSI Approved :: MIT License
Classifier: Operating System :: OS Independent
Requires-Dist: rdflib
Requires-Dist: pyyaml
Requires-Dist: requests
